ntlabs/__init__.py
ntlabs/async_client.py
ntlabs/base.py
ntlabs/client.py
ntlabs/exceptions.py
ntlabs/cache/__init__.py
ntlabs/cache/decorators.py
ntlabs/cache/redis.py
ntlabs/cache/strategies.py
ntlabs/email/__init__.py
ntlabs/email/models.py
ntlabs/email/service.py
ntlabs/email/providers/__init__.py
ntlabs/email/providers/base.py
ntlabs/email/providers/resend.py
ntlabs/email/providers/smtp.py
ntlabs/email/templates/__init__.py
ntlabs/email/templates/renderer.py
ntlabs/export/__init__.py
ntlabs/export/csv.py
ntlabs/export/excel.py
ntlabs/export/pdf.py
ntlabs/export/service.py
ntlabs/export/styles.py
ntlabs/middleware/__init__.py
ntlabs/middleware/cors.py
ntlabs/middleware/logging.py
ntlabs/middleware/rate_limiting.py
ntlabs/middleware/security.py
ntlabs/observability/__init__.py
ntlabs/observability/audit.py
ntlabs/observability/metrics.py
ntlabs/observability/sentry.py
ntlabs/observability/tracing.py
ntlabs/resources/__init__.py
ntlabs/resources/agents.py
ntlabs/resources/async_agents.py
ntlabs/resources/async_auth.py
ntlabs/resources/async_bb.py
ntlabs/resources/async_billing.py
ntlabs/resources/async_cartorio.py
ntlabs/resources/async_chat.py
ntlabs/resources/async_email.py
ntlabs/resources/async_gov.py
ntlabs/resources/async_ibge.py
ntlabs/resources/async_rnds.py
ntlabs/resources/async_saude.py
ntlabs/resources/async_transcribe.py
ntlabs/resources/auth.py
ntlabs/resources/bb.py
ntlabs/resources/billing.py
ntlabs/resources/cartorio.py
ntlabs/resources/chat.py
ntlabs/resources/email.py
ntlabs/resources/gov.py
ntlabs/resources/ibge.py
ntlabs/resources/rnds.py
ntlabs/resources/saude.py
ntlabs/resources/transcribe.py
ntlabs/resources/registros/__init__.py
ntlabs/resources/registros/async_censec.py
ntlabs/resources/registros/async_crc.py
ntlabs/resources/registros/async_enotariado.py
ntlabs/resources/registros/async_onr.py
ntlabs/resources/registros/censec.py
ntlabs/resources/registros/crc.py
ntlabs/resources/registros/enotariado.py
ntlabs/resources/registros/onr.py
ntlabs-1.4.0.dist-info/METADATA
ntlabs-1.4.0.dist-info/WHEEL
ntlabs-1.4.0.dist-info/licenses/LICENSE
ntlabs-1.4.0.dist-info/RECORD
