Metadata-Version: 2.4
Name: ntlabs
Version: 1.4.0
Summary: Python SDK for Neural Thinkers LAB AI Platform - AI Agents, OAuth v2 SSO, Sync and Async Support
Project-URL: Homepage, https://neuralthinkers.up.railway.app
Project-URL: Documentation, https://neuralthinkers.up.railway.app/docs
Project-URL: Repository, https://github.com/NeuralThinkersLab/neural-lab
Author-email: Anderson Henrique da Silva <andersonhs27@gmail.com>
License: Proprietary - Neural Thinker | AI Engineering LTDA
License-File: LICENSE
Keywords: agents,ai,api,chiron,claude,dedalo,hipocrates,llm,maritaca,mercurius,neural-thinkers,ntlabs,polis
Classifier: Development Status :: 4 - Beta
Classifier: Intended Audience :: Developers
Classifier: License :: Other/Proprietary License
Classifier: Programming Language :: Python :: 3
Classifier: Programming Language :: Python :: 3.10
Classifier: Programming Language :: Python :: 3.11
Classifier: Programming Language :: Python :: 3.12
Classifier: Programming Language :: Python :: 3.13
Requires-Python: >=3.10
Requires-Dist: email-validator>=2.0.0
Requires-Dist: httpx>=0.25.0
Requires-Dist: pydantic>=2.0.0
Provides-Extra: cache
Requires-Dist: redis>=5.0.0; extra == 'cache'
Provides-Extra: dev
Requires-Dist: black>=23.0.0; extra == 'dev'
Requires-Dist: mypy>=1.0.0; extra == 'dev'
Requires-Dist: pytest-asyncio>=0.21.0; extra == 'dev'
Requires-Dist: pytest-cov>=4.0.0; extra == 'dev'
Requires-Dist: pytest>=7.0.0; extra == 'dev'
Requires-Dist: ruff>=0.1.0; extra == 'dev'
Provides-Extra: email
Requires-Dist: aiosmtplib>=3.0.0; extra == 'email'
Requires-Dist: jinja2>=3.1.0; extra == 'email'
Provides-Extra: export
Requires-Dist: openpyxl>=3.1.0; extra == 'export'
Requires-Dist: pandas>=2.0.0; extra == 'export'
Requires-Dist: reportlab>=4.0.0; extra == 'export'
Provides-Extra: full
Requires-Dist: aiosmtplib>=3.0.0; extra == 'full'
Requires-Dist: fastapi>=0.100.0; extra == 'full'
Requires-Dist: jinja2>=3.1.0; extra == 'full'
Requires-Dist: openpyxl>=3.1.0; extra == 'full'
Requires-Dist: opentelemetry-exporter-otlp>=1.20.0; extra == 'full'
Requires-Dist: opentelemetry-instrumentation-fastapi>=0.40b0; extra == 'full'
Requires-Dist: opentelemetry-instrumentation-httpx>=0.40b0; extra == 'full'
Requires-Dist: opentelemetry-sdk>=1.20.0; extra == 'full'
Requires-Dist: pandas>=2.0.0; extra == 'full'
Requires-Dist: redis>=5.0.0; extra == 'full'
Requires-Dist: reportlab>=4.0.0; extra == 'full'
Requires-Dist: sentry-sdk>=1.30.0; extra == 'full'
Requires-Dist: starlette>=0.27.0; extra == 'full'
Requires-Dist: supabase>=2.0.0; extra == 'full'
Provides-Extra: middleware
Requires-Dist: fastapi>=0.100.0; extra == 'middleware'
Requires-Dist: redis>=5.0.0; extra == 'middleware'
Requires-Dist: starlette>=0.27.0; extra == 'middleware'
Provides-Extra: observability
Requires-Dist: opentelemetry-exporter-otlp>=1.20.0; extra == 'observability'
Requires-Dist: opentelemetry-instrumentation-fastapi>=0.40b0; extra == 'observability'
Requires-Dist: opentelemetry-instrumentation-httpx>=0.40b0; extra == 'observability'
Requires-Dist: opentelemetry-sdk>=1.20.0; extra == 'observability'
Requires-Dist: sentry-sdk>=1.30.0; extra == 'observability'
Requires-Dist: supabase>=2.0.0; extra == 'observability'
